Workbook

Sheet Read me
A1: House search: Santa Clara, Sunnyvale, Mountain View, North San Jose
A2: Prepared | B2: 27 Oct 2026
A4: Budget (USD) | B4: 2000000
A5: Stretch limit (USD, +5%) | B5: =B4*1.05 -> 2100000
A6: Minimum living area (sq ft) | B6: 1400
A8: Request | B8: Single-family detached house, 3+ bedrooms, 2+ baths, garage; commute to Marvell, 5488 Marvell Lane, Santa Clara, CA 95054 under 20 minutes.
A9: Sheets | B9: Websites = where to search. All listings = every listing reviewed with size/budget checks. Shortlist = homes researched by agents: grocery, school rating, hospital, safety & hazards, commute, scores.
A10: Edit | B10: Yellow cells are inputs: change the budget or minimum size and every pass/fail check recalculates. Blue cells are prices and scores you can update.
A11: Scoring | B11: Safety, Livability, Value, Verification are 1-5 from the research agents. Total = Safety + Livability + Value + 2 x Verification. The main pick also had to meet the 20-minute commute.
A12: Ongoing costs | B12: California property tax is roughly 1.1-1.25% of the purchase price per year (~$22-25K on $2M), plus homeowner's insurance (earthquake cover is separate) and any HOA / Mello-Roos.
A13: Caveats | B13: Zillow, Redfin and homes.com detail pages often blocked automated reading, so some facts come from MLS/brokerage pages or same-plan neighbours. Distances and commute times are estimates; check FEMA flood zones at msc.fema.gov and school assignment by address.

Sheet Websites
A1: Website | B1: URL | C1: Why use it
A2: Zillow | B2: https://www.zillow.com | C2: Largest US portal; Zestimates and price/tax history. Blocks automated reading - browse it yourself.
A3: Redfin | B3: https://www.redfin.com | C3: Fast MLS updates, sold comps, Flood Factor and school data; partly blocked for automated reading.
A4: Realtor.com | B4: https://www.realtor.com | C4: MLS-fed listings, often the most up-to-date status (pending/contingent).
A5: Homes.com | B5: https://www.homes.com | C5: Clean city/ZIP lists with price-drop tags; main source for this shortlist.
A6: MLSListings | B6: https://www.mlslistings.com | C6: The Bay Area MLS itself; city market stats (median, $/sqft, days on market).
A7: Brokerage sites (Compass, Coldwell Banker, Sereno, RE/MAX) | B7: https://www.coldwellbankerhomes.com | C7: Full MLS detail pages that usually load when portals block.
A8: GreatSchools | B8: https://www.greatschools.org | C8: School ratings and assigned-school lookups by address.
A9: FEMA Flood Map Service Center | B9: https://msc.fema.gov | C9: Official flood zone for each address (affects insurance).

Sheet All listings
A1: # | B1: City | C1: Address | D1: Link | E1: Price ($) | F1: Beds | G1: Baths | H1: Living sq ft | I1: $ / sq ft | J1: >= min sq ft? | K1: 3+ bd & 2+ ba? | L1: Within budget? | M1: Outcome / reason
A2: 1 | B2: Santa Clara | C2: 3021 Santa Maria Ave, 95051 | D2: Open listing | E2: 1799000 | F2: 4 | G2: 3 | H2: 1586 | I2: =E2/H2 -> 1134.3001 | J2: =IF(H2>='Read me'!$B$6,"Yes","No") -> Yes | K2: =IF(AND(F2>=3,G2>=2),"Yes","No") -> Yes | L2: =IF(E2<='Read me'!$B$4,"Yes",IF(E2<='Read me'!$B$5,"Stretch","No")) -> Yes | M2: Shortlisted SC-1
A3: 2 | B3: Santa Clara | C3: 2044 Finley Pl, 95050 | D3: Open listing | E3: 2498000 | F3: 4 | G3: 3 | H3: 2360 | I3: =E3/H3 -> 1058.4746 | J3: =IF(H3>='Read me'!$B$6,"Yes","No") -> Yes | K3: =IF(AND(F3>=3,G3>=2),"Yes","No") -> Yes | L3: =IF(E3<='Read me'!$B$4,"Yes",IF(E3<='Read me'!$B$5,"Stretch","No")) -> No | M3: Over budget
A4: 3 | B4: Santa Clara | C4: 3483 Emmett Pl, 95051 | D4: Open listing | E4: 1899000 | F4: 3 | G4: 2 | H4: 1302 | I4: =E4/H4 -> 1458.5253 | J4: =IF(H4>='Read me'!$B$6,"Yes","No") -> No | K4: =IF(AND(F4>=3,G4>=2),"Yes","No") -> Yes | L4: =IF(E4<='Read me'!$B$4,"Yes",IF(E4<='Read me'!$B$5,"Stretch","No")) -> Yes | M4: Under 1,400 sq ft
A5: 4 | B5: Santa Clara | C5: 3015 Machado Ave, 95051 | D5: Open listing | E5: 2499000 | F5: 4 | G5: 3 | H5: 2019 | I5: =E5/H5 -> 1237.7415 | J5: =IF(H5>='Read me'!$B$6,"Yes","No") -> Yes | K5: =IF(AND(F5>=3,G5>=2),"Yes","No") -> Yes | L5: =IF(E5<='Read me'!$B$4,"Yes",IF(E5<='Read me'!$B$5,"Stretch","No")) -> No | M5: Over budget
A6: 5 | B6: Santa Clara | C6: 679 Cupples Ct, 95051 | D6: Open listing | E6: 2950000 | F6: 4 | G6: 3 | H6: 2375 | I6: =E6/H6 -> 1242.1053 | J6: =IF(H6>='Read me'!$B$6,"Yes","No") -> Yes | K6: =IF(AND(F6>=3,G6>=2),"Yes","No") -> Yes | L6: =IF(E6<='Read me'!$B$4,"Yes",IF(E6<='Read me'!$B$5,"Stretch","No")) -> No | M6: Over budget
A7: 6 | B7: Santa Clara | C7: 1718 Pomeroy Ave, 95051 | D7: Open listing | E7: 1688000 | F7: 3 | G7: 2 | H7: 1080 | I7: =E7/H7 -> 1562.963 | J7: =IF(H7>='Read me'!$B$6,"Yes","No") -> No | K7: =IF(AND(F7>=3,G7>=2),"Yes","No") -> Yes | L7: =IF(E7<='Read me'!$B$4,"Yes",IF(E7<='Read me'!$B$5,"Stretch","No")) -> Yes | M7: Under 1,400 sq ft
A8: 7 | B8: Santa Clara | C8: 621 Hilmar St, 95050 | D8: Open listing | E8: 2178000 | F8: 3 | G8: 2.5 | H8: 2671 | I8: =E8/H8 -> 815.42493 | J8: =IF(H8>='Read me'!$B$6,"Yes","No") -> Yes | K8: =IF(AND(F8>=3,G8>=2),"Yes","No") -> Yes | L8: =IF(E8<='Read me'!$B$4,"Yes",IF(E8<='Read me'!$B$5,"Stretch","No")) -> No | M8: Over budget (>5%)
A9: 8 | B9: Santa Clara | C9: 5019 Avenida de Lago, 95054 | D9: Open listing | E9: 1968888 | F9: 4 | G9: 2 | H9: 1584 | I9: =E9/H9 -> 1242.9848 | J9: =IF(H9>='Read me'!$B$6,"Yes","No") -> Yes | K9: =IF(AND(F9>=3,G9>=2),"Yes","No") -> Yes | L9: =IF(E9<='Read me'!$B$4,"Yes",IF(E9<='Read me'!$B$5,"Stretch","No")) -> Yes | M9: Shortlisted SC-2
A10: 9 | B10: Santa Clara | C10: 1659 Hood Ct, 95051 | D10: Open listing | E10: 2388000 | F10: 5 | G10: 4 | H10: 2035 | I10: =E10/H10 -> 1173.4644 | J10: =IF(H10>='Read me'!$B$6,"Yes","No") -> Yes | K10: =IF(AND(F10>=3,G10>=2),"Yes","No") -> Yes | L10: =IF(E10<='Read me'!$B$4,"Yes",IF(E10<='Read me'!$B$5,"Stretch","No")) -> No | M10: Over budget
A11: 10 | B11: Santa Clara | C11: 376 Cypress Ave, 95050 | D11: Open listing | E11: 2388000 | F11: 4 | G11: 2 | H11: 1817 | I11: =E11/H11 -> 1314.2543 | J11: =IF(H11>='Read me'!$B$6,"Yes","No") -> Yes | K11: =IF(AND(F11>=3,G11>=2),"Yes","No") -> Yes | L11: =IF(E11<='Read me'!$B$4,"Yes",IF(E11<='Read me'!$B$5,"Stretch","No")) -> No | M11: Over budget
A12: 11 | B12: Santa Clara | C12: 1152 Pierce St, 95050 | D12: Open listing | E12: 1280000 | F12: 3 | G12: 2 | H12: 998 | I12: =E12/H12 -> 1282.5651 | J12: =IF(H12>='Read me'!$B$6,"Yes","No") -> No | K12: =IF(AND(F12>=3,G12>=2),"Yes","No") -> Yes | L12: =IF(E12<='Read me'!$B$4,"Yes",IF(E12<='Read me'!$B$5,"Stretch","No")) -> Yes | M12: Under 1,400 sq ft
A13: 12 | B13: Santa Clara | C13: 646 Bucher Ave, 95051 | D13: Open listing | E13: 1988000 | F13: 3 | G13: 2 | H13: 1518 | I13: =E13/H13 -> 1309.6179 | J13: =IF(H13>='Read me'!$B$6,"Yes","No") -> Yes | K13: =IF(AND(F13>=3,G13>=2),"Yes","No") -> Yes | L13: =IF(E13<='Read me'!$B$4,"Yes",IF(E13<='Read me'!$B$5,"Stretch","No")) -> Yes | M13: Shortlisted SC-3
... A71: 70 | B71: North San Jose | C71: 1753 Ridgetree Way, 95131 | D71: Open listing | E71: 2088888 | F71: 4 | G71: 3 | H71: 2400 | I71: =E71/H71 -> 870.37 | J71: =IF(H71>='Read me'!$B$6,"Yes","No") -> Yes | K71: =IF(AND(F71>=3,G71>=2),"Yes","No") -> Yes | L71: =IF(E71<='Read me'!$B$4,"Yes",IF(E71<='Read me'!$B$5,"Stretch","No")) -> Stretch | M71: Shortlisted NS-11 (stretch)

Sheet Shortlist
A1: ID | B1: City | C1: Address | D1: Link | E1: Living sq ft | F1: Lot (sq ft) | G1: Bed/Bath | H1: Garage | I1: Year | J1: HOA | K1: Status / history | L1: Price ($) | M1: $ / sq ft | N1: Grocery | O1: Elementary school (rating) | P1: Hospital (ER) | Q1: Safety & hazards | R1: Commute to Marvell | S1: Red flags | T1: Safety 1-5 | U1: Livability 1-5 | V1: Value 1-5 | W1: Verification 1-5 | X1: Total score | Y1: Rank (all) | Z1: Within budget? | AA1: Status
A2: SC-7 | B2: Santa Clara | C2: 2831 Monroe St, Santa Clara 95051 | D2: Open listing | E2: 1815 | F2: 7,000 (corner) | G2: 4/2 | H2: 2-car attached | I2: 1958 | J2: None | K2: Active, ~44-68 days; cut $410K from $2.499M on 9/9/2026 | L2: 1988888 | M2: =L2/E2 -> 1095.8061 | N2: Lucky/Safeway on El Camino ~1 mi (est.) | O2: Bracher Elem (Santa Clara USD) 6/10, 0.27 mi; Bowers 7/10 0.43 mi | P2: Kaiser Santa Clara Medical Center (ER) ~2 mi | Q2: Santa Clara violent crime below US average (city-data); flood zone likely X - verify; possible San Tomas Expwy noise. | R2: 15-20 min | S2: Motivated seller after big cuts; 'fully permitted' expansion - get permit copies; corner lot sees more traffic. | T2: 4 | U2: 4 | V2: 5 | W2: 4 | X2: =T2+U2+V2+2*W2 -> 21 | Y2: =RANK(X2,$X$2:$X$30) -> 2 | Z2: =IF(L2<='Read me'!$B$4,"Yes",IF(L2<='Read me'!$B$5,"Stretch","No")) -> Yes | AA2: MAIN PICK
A3: SC-5 | B3: Santa Clara | C3: 2527 Malone Pl, Santa Clara 95050 | D3: Open listing | E3: 1617 | F3: 6,534 | G3: 3/2 + 1/1 ADU | H3: 2-car attached | I3: 1957 | J3: None | K3: Active, 66 days; cut $300K | L3: 1995000 | M3: =L3/E3 -> 1233.7662 | N3: Safeway/Lucky, Homestead Rd ~1 mi (est.) | O3: C.W. Haman Elem (Santa Clara USD) 6/10, 0.4 mi; Millikin 10/10 nearby (choice school) | P3: Kaiser Santa Clara (ER) ~1.5-2 mi | Q3: Central Santa Clara, average-to-low crime; away from the Bay so lower flood/liquefaction risk (verify). | R3: 15-18 min | S3: Right at the budget cap; permitted ADU with its own address (2529 Malone) - rental income or family suite. | T3: 4 | U3: 5 | V3: 4 | W3: 4 | X3: =T3+U3+V3+2*W3 -> 21 | Y3: =RANK(X3,$X$2:$X$30) -> 2 | Z3: =IF(L3<='Read me'!$B$4,"Yes",IF(L3<='Read me'!$B$5,"Stretch","No")) -> Yes | AA3: Alternative #1
A4: NS-6 | B4: North San Jose | C4: 1094 Rock Ave, San Jose 95131 | D4: Open listing | E4: 1828 | F4: 3,000 | G4: 3/2.5 | H4: 2-car | I4: 2005 | J4: $0 (verify) | K4: Active, ~47 days | L4: 1598000 | M4: =L4/E4 -> 874.17943 | N4: 99 Ranch Market, Milpitas Square ~2 mi (est.) | O4: Orchard Elem K-8 (Orchard SD) 5/10, 0.3 mi | P4: Regional Medical Center of San Jose (ER) ~5 mi | Q4: Mixed residential/industrial Oakland Rd area, crime ~San Jose average; Redfin Flood Factor 5/10 - flood insurance likely; rail/truck noise. | R4: 15-20 min | S4: Small lot; former rental; flood risk. | T4: 3 | U4: 3 | V4: 4 | W4: 5 | X4: =T4+U4+V4+2*W4 -> 20 | Y4: =RANK(X4,$X$2:$X$30) -> 4 | Z4: =IF(L4<='Read me'!$B$4,"Yes",IF(L4<='Read me'!$B$5,"Stretch","No")) -> Yes | AA4: Alternative #2
A5: SV-4 | B5: Sunnyvale | C5: 1181 Blazingwood Dr, Sunnyvale 94089 (Lakewood Village) | D5: Open listing | E5: 1528 | F5: 5,670 | G5: 3/2 | H5: 2-car attached | I5: 1958 | J5: None | K5: Active (~65 days); bought $1.25M Jun 2026, remodeled flip | L5: 1499888 | M5: =L5/E5 -> 981.60209 | N5: New Wing Yuan Market, Lakewood Shopping Center ~0.5 mi | O5: Fairwood Elem (Sunnyvale SD) 9/10, 0.3 mi; Fremont High 9/10 | P5: Kaiser Santa Clara (ER) ~2.5 mi | Q5: Sunnyvale crime below CA average (NeighborhoodScout); Flood Factor 1/10; Hwy 237/Lawrence noise ~0.5 mi. | R5: 8-12 min | S5: Investor flip (+$250K in 2 months) - ask for permits and the full work list; local grocery center may be redeveloped. | T5: 3 | U5: 4 | V5: 5 | W5: 4 | X5: =T5+U5+V5+2*W5 -> 20 | Y5: =RANK(X5,$X$2:$X$30) -> 4 | Z5: =IF(L5<='Read me'!$B$4,"Yes",IF(L5<='Read me'!$B$5,"Stretch","No")) -> Yes | AA5: Alternative #3
A6: SV-8 | B6: Sunnyvale | C6: 348 Angel Ave, Sunnyvale 94086 | D6: Open listing | E6: 2428 | F6: 6,400 | G6: 5/4 (incl. 1/1 ADU) | H6: Detached 2-car + EV, ADU above | I6: 2026 | J6: None | K6: Active, new construction; relisted $3.588M -> $2.98M -> $1.988M | L6: 1988000 | M6: =L6/E6 -> 818.78089 | N6: Safeway on El Camino / downtown ~0.8 mi (est.) | O6: Bishop Elem (Sunnyvale SD) 7/10, 0.7 mi; Fremont High 9/10 | P6: Kaiser Santa Clara (ER) ~3 mi | Q6: Central Sunnyvale, crime near city average; possible Caltrain/Central Expwy noise. | R6: 10-14 min | S6: Priced to start a bidding war - expect final price well above $2M; confirm final inspection / certificate of occupancy. | T6: 3 | U6: 5 | V6: 3 | W6: 4 | X6: =T6+U6+V6+2*W6 -> 19 | Y6: =RANK(X6,$X$2:$X$30) -> 7 | Z6: =IF(L6<='Read me'!$B$4,"Yes",IF(L6<='Read me'!$B$5,"Stretch","No")) -> Yes | AA6: Alternative #4
A7: SC-1 | B7: Santa Clara | C7: 3021 Santa Maria Ave, Santa Clara 95051 (Bowers Crest) | D7: Open listing | E7: 1586 | F7: ~5,550 | G7: 4/3 (2 primary suites) | H7: 2-car attached | I7: 1955 | J7: None | K7: Active, just listed | L7: 1799000 | M7: =L7/E7 -> 1134.3001 | N7: Bowers Plaza / El Camino centers ~0.9 mi | O7: Likely Bowers Elem (Santa Clara USD) 7/10, ~0.5-1 mi | P7: Kaiser Santa Clara (ER) ~1.5 mi | Q7: Santa Clara violent crime about half the US rate (city-data); flood zone likely X; occasional SJC aircraft noise. | R7: 12-18 min | S7: Below city median $/sqft - expect multiple offers; confirm school assignment. | T7: 4 | U7: 4 | V7: 5 | W7: 3 | X7: =T7+U7+V7+2*W7 -> 19 | Y7: =RANK(X7,$X$2:$X$30) -> 7 | Z7: =IF(L7<='Read me'!$B$4,"Yes",IF(L7<='Read me'!$B$5,"Stretch","No")) -> Yes | AA7: Alternative #5
A8: SC-3 | B8: Santa Clara | C8: 646 Bucher Ave, Santa Clara 95051 (Mariposa Gardens) | D8: Open listing | E8: 1518 | F8: 5,247 | G8: 3/2 | H8: 2-car attached + EV | I8: 1954 | J8: None | K8: Active, 82 days; cut $100K | L8: 1988000 | M8: =L8/E8 -> 1309.6179 | N8: Safeway, 2760 Homestead Rd ~0.8 mi | O8: Westwood Elem (Santa Clara USD) 6/10, 0.5 mi; Millikin 10/10 (choice) | P8: Kaiser Santa Clara (ER) ~1.2 mi | Q8: Quiet residential street; flood zone likely X. | R8: 15-20 min | S8: Long time on market, above median $/sqft - room to negotiate; expansion permits. | T8: 4 | U8: 4 | V8: 3 | W8: 4 | X8: =T8+U8+V8+2*W8 -> 19 | Y8: =RANK(X8,$X$2:$X$30) -> 7 | Z8: =IF(L8<='Read me'!$B$4,"Yes",IF(L8<='Read me'!$B$5,"Stretch","No")) -> Yes | AA8: Alternative #6
A9: NS-9 | B9: North San Jose | C9: 1873 Silkwood Ln, San Jose 95131 | D9: Open listing | E9: 1828 | F9: 3,139 | G9: 3/2.5 | H9: 2-car attached | I9: 2007 | J9: None listed | K9: Active, ~41 days | L9: 1598000 | M9: =L9/E9 -> 874.17943 | N9: 99 Ranch Market, Milpitas Square ~2 mi (est.) | O9: Orchard Elem K-8 (Orchard SD) 5/10, ~0.4 mi | P9: Regional Medical Center of San Jose (ER) ~5 mi | Q9: Same area as NS-6: crime ~city average, moderate flood/liquefaction, rail noise. | R9: 15-20 min | S9: Small lot; check flood factor. | T9: 3 | U9: 3 | V9: 4 | W9: 4 | X9: =T9+U9+V9+2*W9 -> 18 | Y9: =RANK(X9,$X$2:$X$30) -> 11 | Z9: =IF(L9<='Read me'!$B$4,"Yes",IF(L9<='Read me'!$B$5,"Stretch","No")) -> Yes | AA9: Alternative #7
A10: SV-7 | B10: Sunnyvale | C10: 1213 Manet Dr, Sunnyvale 94087 | D10: Open listing | E10: 1552 | F10: 2,755 | G10: 3/2.5 | H10: 2-car attached | I10: 1976 | J10: None | K10: Active, ~96 days; cut ~$200-300K | L10: 1998000 | M10: =L10/E10 -> 1287.3711 | N10: Safeway/Lucky, Hollenbeck-El Camino ~1 mi (est.) | O10: Stocklmeir Elem (Cupertino USD) 10/10 per listing - verify; Cupertino Middle 9/10 | P10: El Camino Hospital Mountain View (ER) ~3.5 mi | Q10: Low-crime southwest Sunnyvale; flood zone likely X. | R10: 16-20 min | S10: Very small lot; school assignment conflicts in MLS - verify with Cupertino USD. | T10: 5 | U10: 3 | V10: 4 | W10: 3 | X10: =T10+U10+V10+2*W10 -> 18 | Y10: =RANK(X10,$X$2:$X$30) -> 11 | Z10: =IF(L10<='Read me'!$B$4,"Yes",IF(L10<='Read me'!$B$5,"Stretch","No")) -> Yes | AA10: Alternative #8
A11: SV-1 | B11: Sunnyvale | C11: 807 S Wolfe Rd, Sunnyvale 94086 | D11: Open listing | E11: 1617 | F11: 7,000 | G11: 4/2 + office | H11: 2-car | I11: 1965 | J11: None | K11: Active, ~26 days; cut $100K | L11: 2098888 | M11: =L11/E11 -> 1298.0136 | N11: Safeway/Lucky on El Camino ~0.8 mi (est.) | O11: Likely Ponderosa Elem (Sunnyvale SD) ~6-7/10 (est.); Fremont High 9/10 | P11: Kaiser Santa Clara (ER) ~2.5 mi | Q11: Sunnyvale crime below CA average; fronts 4-lane Wolfe Rd (traffic noise). | R11: 12-16 min | S11: 5% over budget; busy-road frontage hurts resale. | T11: 4 | U11: 3 | V11: 3 | W11: 4 | X11: =T11+U11+V11+2*W11 -> 18 | Y11: =RANK(X11,$X$2:$X$30) -> 11 | Z11: =IF(L11<='Read me'!$B$4,"Yes",IF(L11<='Read me'!$B$5,"Stretch","No")) -> Stretch | AA11: Alternative #9
A12: NS-5 | B12: North San Jose | C12: 1317 Dryden Dr, San Jose 95131 (Berryessa) | D12: Open listing | E12: 1538 | F12: 6,000 | G12: 3/2.5 | H12: 2-car attached | I12: 1971 | J12: None | K12: Active, listed 10/21/2026 | L12: 1650000 | M12: =L12/E12 -> 1072.8218 | N12: Safeway, Berryessa Rd ~1.2 mi | O12: Vinci Park Elem (Berryessa Union SD) 8/10, 0.2 mi | P12: Regional Medical Center of San Jose (ER) ~4 mi | Q12: Berryessa is one of San Jose's safer areas (Niche A-); I-680 ~0.5 mi. | R12: 20-25 min (over limit) | S12: Priced $210K under its 2024 sale - expect bidding; commute slightly over 20 min. | T12: 4 | U12: 5 | V12: 3 | W12: 5 | X12: =T12+U12+V12+2*W12 -> 22 | Y12: =RANK(X12,$X$2:$X$30) -> 1 | Z12: =IF(L12<='Read me'!$B$4,"Yes",IF(L12<='Read me'!$B$5,"Stretch","No")) -> Yes | AA12: Alternative #10
A13: NS-7 | B13: North San Jose | C13: 1459 Goldenlake Rd, San Jose 95131 (Berryessa) | D13: Open listing | E13: 2591 | F13: 6,090 | G13: 6/4 | H13: 2-car attached | I13: 1974 | J13: None | K13: Active, listed 10/22/2026; bought $1.6M Jul 2026 (flip) | L13: 1830000 | M13: =L13/E13 -> 706.29101 | N13: Lundy/Berryessa corridor stores ~1-1.5 mi (est.) | O13: Brooktree Elem (Berryessa Union SD) 6/10, 0.8 mi | P13: Regional Medical Center of San Jose (ER) ~4 mi | Q13: Berryessa generally below SJ average crime (unverified); I-680/SJC noise. | R13: 18-25 min (borderline) | S13: Fast flip - pull permits; commute borderline. | T13: 4 | U13: 4 | V13: 4 | W13: 4 | X13: =T13+U13+V13+2*W13 -> 20 | Y13: =RANK(X13,$X$2:$X$30) -> 4 | Z13: =IF(L13<='Read me'!$B$4,"Yes",IF(L13<='Read me'!$B$5,"Stretch","No")) -> Yes
A14: SV-2 | B14: Sunnyvale | C14: 1389 Sydney Dr, Sunnyvale 94087 | D14: Open listing | E14: 1585 | F14: ~4,350 | G14: 3/2 + loft | H14: 2-car attached | I14: 1971 | J14: None shown | K14: Active, ~33 days | L14: 2098000 | M14: =L14/E14 -> 1323.6593 | N14: Safeway/Nob Hill ~1 mi (est.) | O14: Nimitz Elem (Cupertino USD) 6/10, 0.1 mi; Cupertino Middle 9/10; Fremont High 9/10 | P14: El Camino Hospital Mountain View (ER) ~3.5 mi | Q14: One of Sunnyvale's safest areas (NeighborhoodScout); flood zone likely X. | R14: 18-22 min (borderline) | S14: 'Patio home' - confirm detached and not in the Woodgate townhouse HOA; 5% over budget. | T14: 5 | U14: 4 | V14: 3 | W14: 3 | X14: =T14+U14+V14+2*W14 -> 18 | Y14: =RANK(X14,$X$2:$X$30) -> 11 | Z14: =IF(L14<='Read me'!$B$4,"Yes",IF(L14<='Read me'!$B$5,"Stretch","No")) -> Stretch
A15: NS-11 | B15: North San Jose | C15: 1753 Ridgetree Way, San Jose 95131 (Tennyson Woods) | D15: Open listing | E15: 2400 | F15: 6,000 | G15: 4/3 | H15: 3-car attached | I15: 1979 | J15: None | K15: Active, listed 10/21/2026 | L15: 2088888 | M15: =L15/E15 -> 870.37 | N15: Lundy Ave / Sierra Rd stores ~1-1.5 mi (est.) | O15: Brooktree Elem (Berryessa Union SD) 6/10, 0.1 mi | P15: Regional Medical Center of San Jose (ER) ~4.5 mi | Q15: Established Berryessa neighbourhood; some I-680 noise. | R15: 20-25 min (over limit) | S15: 4.4% over budget; 32-year owner - check roof, plumbing, electrical; split-level stairs. | T15: 4 | U15: 4 | V15: 3 | W15: 4 | X15: =T15+U15+V15+2*W15 -> 19 | Y15: =RANK(X15,$X$2:$X$30) -> 7 | Z15: =IF(L15<='Read me'!$B$4,"Yes",IF(L15<='Read me'!$B$5,"Stretch","No")) -> Stretch
A16: SC-2 | B16: Santa Clara | C16: 5019 Avenida de Lago, Santa Clara 95054 | D16: Open listing | E16: 1584 | F16: 6,500 | G16: 4/2 | H16: 2-car attached (tract, est.) | I16: 1976 | J16: None | K16: Active | L16: 1968888 | M16: =L16/E16 -> 1242.9848 | N16: Safeway, Rivermark Village ~1 mi | O16: Kathryn Hughes Elem (Santa Clara USD) 6/10, 0.2 mi | P16: Kaiser Santa Clara (ER) ~4.5 mi | Q16: Quiet tract; liquefaction likely (Bay mud); Levi's Stadium / SJC noise. | R16: 8-12 min | S16: Priced ~$300K above an as-is twin sale ($1.66M) - you pay for the remodel; check permits. | T16: 4 | U16: 4 | V16: 3 | W16: 3 | X16: =T16+U16+V16+2*W16 -> 17 | Y16: =RANK(X16,$X$2:$X$30) -> 16 | Z16: =IF(L16<='Read me'!$B$4,"Yes",IF(L16<='Read me'!$B$5,"Stretch","No")) -> Yes
A17: SC-8 | B17: Santa Clara | C17: 2005 Stanley Ave, Santa Clara 95050 (Westwood) | D17: Open listing | E17: 1420 | F17: 7,000 | G17: 3/3 | H17: 2-car | I17: 1955 | J17: None | K17: Active, listed 10/14/2026 | L17: 1899950 | M17: =L17/E17 -> 1337.993 | N17: Lucky/Safeway ~1 mi (est.) | O17: Westwood Elem (Santa Clara USD) 6/10, 0.5 mi | P17: Kaiser Santa Clara (ER) ~1.5 mi | Q17: Redfin Flood Factor 5/10 (56-68% over 30 yrs); San Tomas / I-280 noise. | R17: 15-20 min | S17: High vs. a $1.65M sale across the street; check addition permits; flood insurance. | T17: 3 | U17: 4 | V17: 2 | W17: 4 | X17: =T17+U17+V17+2*W17 -> 17 | Y17: =RANK(X17,$X$2:$X$30) -> 16 | Z17: =IF(L17<='Read me'!$B$4,"Yes",IF(L17<='Read me'!$B$5,"Stretch","No")) -> Yes
A18: MV-2 | B18: Mountain View | C18: 3818 Pyramid Way, Mountain View 94043 | D18: Open listing | E18: 1751 | F18: ~1,425 | G18: 4/4 | H18: 2-car attached | I18: 2019 | J18: ~$186/mo | K18: Active; cut $238K | L18: 1750000 | M18: =L18/E18 -> 999.4289 | N18: Safeway, 570 N Shoreline ~2 mi (est.) | O18: Jose Antonio Vargas Elem (MV Whisman SD) 8/10, 0.3 mi | P18: El Camino Hospital Mountain View (ER) ~3 mi | Q18: Quiet Whisman area; near MEW Superfund groundwater plume (ask for vapor disclosure); light-rail/Moffett noise. | R18: 12-18 min | S18: Small-lot 3-story detached home; data from same-plan sale (listing blocked) - verify; Mello-Roos check. | T18: 4 | U18: 4 | V18: 5 | W18: 2 | X18: =T18+U18+V18+2*W18 -> 17 | Y18: =RANK(X18,$X$2:$X$30) -> 16 | Z18: =IF(L18<='Read me'!$B$4,"Yes",IF(L18<='Read me'!$B$5,"Stretch","No")) -> Yes
A19: MV-1 | B19: Mountain View | C19: 3312 Pyramid Way, Mountain View 94043 | D19: Open listing | E19: 1781 | F19: ~1,425 | G19: 3/3.5 | H19: 2-car attached | I19: 2018 | J19: ~$186/mo | K19: Active | L19: 1988000 | M19: =L19/E19 -> 1116.2268 | N19: Safeway, 570 N Shoreline ~2 mi (est.) | O19: Jose Antonio Vargas Elem (MV Whisman SD) 8/10, 0.3 mi | P19: El Camino Hospital Mountain View (ER) ~3 mi | Q19: Same as MV-2. | R19: 12-18 min | S19: Same-plan twin sold $2.125M - fair price; tiny lot; vapor disclosure. | T19: 4 | U19: 4 | V19: 4 | W19: 2 | X19: =T19+U19+V19+2*W19 -> 16 | Y19: =RANK(X19,$X$2:$X$30) -> 21 | Z19: =IF(L19<='Read me'!$B$4,"Yes",IF(L19<='Read me'!$B$5,"Stretch","No")) -> Yes
A20: NS-1 | B20: North San Jose | C20: 4213 Verdigris Cir, San Jose 95134 (Renaissance) | D20: Open listing | E20: 1828 | F20: ~2,500 (est.) | G20: 3/2.5 | H20: 2-car attached (est.) | I20: 1996 | J20: Small (verify) | K20: Active, first time on market | L20: 1775000 | M20: =L20/E20 -> 971.00656 | N20: Safeway, Rivermark Plaza ~1 mi | O20: Don Callejon K-8 (Santa Clara USD) ~7/10 (est.), 0.5 mi | P20: Kaiser Santa Clara (ER) ~4 mi | Q20: Crime at/below SJ average (est.); mapped liquefaction zone; FEMA X behind levees likely; VTA/Hwy 237 noise. | R20: 10-12 min | S20: Listing blocked - details unverified; a smaller house on the same street sold $1.88M, so expect offers. | T20: 4 | U20: 4 | V20: 4 | W20: 2 | X20: =T20+U20+V20+2*W20 -> 16 | Y20: =RANK(X20,$X$2:$X$30) -> 21 | Z20: =IF(L20<='Read me'!$B$4,"Yes",IF(L20<='Read me'!$B$5,"Stretch","No")) -> Yes
A21: SC-6 | B21: Santa Clara | C21: 2199 Avenida de Las Flores, Santa Clara 95054 | D21: Open listing | E21: 1563 | F21: 7,125 | G21: 3/2 | H21: Attached | I21: 1976 | J21: None | K21: Active - Zillow tags PRE-FORECLOSURE | L21: 1399000 | M21: =L21/E21 -> 895.07358 | N21: Safeway, Rivermark ~1 mi | O21: Kathryn Hughes Elem (Santa Clara USD) 6/10, 0.3 mi | P21: Kaiser Santa Clara (ER) ~4.5 mi | Q21: Same quiet tract as SC-2. | R21: 8-12 min | S21: Distressed sale: lender/timing risk, as-is, dated interior; price shown $1.399M-$1.599M. | T21: 4 | U21: 4 | V21: 4 | W21: 2 | X21: =T21+U21+V21+2*W21 -> 16 | Y21: =RANK(X21,$X$2:$X$30) -> 21 | Z21: =IF(L21<='Read me'!$B$4,"Yes",IF(L21<='Read me'!$B$5,"Stretch","No")) -> Yes
A22: NS-10 | B22: North San Jose | C22: 1357 Goldenlake Rd, San Jose 95131 (Berryessa) | D22: Open listing | E22: 1960 | F22: ~6,000 (est.) | G22: 4/2.5 | H22: Likely | I22: 1973 | J22: Likely none | K22: Active | L22: 1499000 | M22: =L22/E22 -> 764.79592 | N22: Safeway, Berryessa Rd ~1.3 mi | O22: Brooktree Elem 6/10 ~0.9 mi (maybe Vinci Park 8/10) | P22: Regional Medical Center of San Jose (ER) ~4 mi | Q22: Quiet Berryessa (Niche A-); low flood risk. | R22: 20-25 min (over limit) | S22: Fixer - budget $100-250K+; details unconfirmed. | T22: 4 | U22: 4 | V22: 4 | W22: 2 | X22: =T22+U22+V22+2*W22 -> 16 | Y22: =RANK(X22,$X$2:$X$30) -> 21 | Z22: =IF(L22<='Read me'!$B$4,"Yes",IF(L22<='Read me'!$B$5,"Stretch","No")) -> Yes
A23: SV-3 | B23: Sunnyvale | C23: 813 San Petronio Ave, Sunnyvale 94085 | D23: Open listing | E23: 1640 | F23: ~5,600 (est.) | G23: 3/2 + office | H23: NOT confirmed | I23: 1955 | J23: Likely none | K23: Active | L23: 1898500 | M23: =L23/E23 -> 1157.622 | N23: Fair Oaks / Arques markets ~1 mi (est.) | O23: San Miguel Elem (Sunnyvale SD) 5/10, 0.2 mi; Fremont High 9/10 | P23: Kaiser Santa Clara (ER) ~3 mi | Q23: Check FEMA zone; some Hwy 101 noise. | R23: 12-15 min | S23: Least verified; garage unconfirmed; office permits. | T23: 3 | U23: 3 | V23: 3 | W23: 2 | X23: =T23+U23+V23+2*W23 -> 13 | Y23: =RANK(X23,$X$2:$X$30) -> 28 | Z23: =IF(L23<='Read me'!$B$4,"Yes",IF(L23<='Read me'!$B$5,"Stretch","No")) -> Yes
A24: NS-8 | B24: North San Jose | C24: 1367 Shore Dr, San Jose 95131 | D24: Open listing | E24: 2250 | F24: 3,252 | G24: 5/5 | H24: 2-car | I24: 2014 | J24: Unknown | K24: Active, ~34 days | L24: 1999888 | M24: =L24/E24 -> 888.83911 | N24: Market Park Plaza area ~1 mi (est.) | O24: Vinci Park Elem (Berryessa Union SD) 8/10, 0.7 mi | P24: Regional Medical Center of San Jose (ER) ~4 mi | Q24: Moderate crime (unverified); FEMA 'D' nearby; Oakland Rd/I-880/SJC noise. | R24: 15-22 min | S24: Tiny lot; high vs. 1399 Shore Dr sale ($1.75M). | T24: 3 | U24: 4 | V24: 2 | W24: 3 | X24: =T24+U24+V24+2*W24 -> 15 | Y24: =RANK(X24,$X$2:$X$30) -> 26 | Z24: =IF(L24<='Read me'!$B$4,"Yes",IF(L24<='Read me'!$B$5,"Stretch","No")) -> Yes
A25: NS-2 | B25: North San Jose | C25: 681 Epic Way (Pyrus Place), San Jose 95134 | D25: Open listing | E25: 1827 | F25: - | G25: 3/3.5 | H25: 2-car + EV | I25: 2026 | J25: $370/mo | K25: Relisted at $1.58M | L25: 1488000 | M25: =L25/E25 -> 814.44992 | N25: Safeway Rivermark ~2 mi | O25: Montague Elem 5/10 ~2.5 mi | P25: Kaiser Santa Clara ~5 mi | Q25: Average crime; liquefaction; construction noise. | R25: 12-15 min | S25: MLS lists it as a 3-story TOWNHOUSE - not a detached house. | T25: 3 | U25: 3 | V25: 3 | W25: 4 | X25: =T25+U25+V25+2*W25 -> 17 | Y25: =RANK(X25,$X$2:$X$30) -> 16 | Z25: =IF(L25<='Read me'!$B$4,"Yes",IF(L25<='Read me'!$B$5,"Stretch","No")) -> Yes | AA25: Avoid
A26: NS-3 | B26: North San Jose | C26: 687 Epic Way (Pyrus Place), San Jose 95134 | D26: Open listing | E26: 1987 | F26: - | G26: 4/3.5 | H26: 2-car + EV | I26: 2026 | J26: $375/mo | K26: Active, 29 days | L26: 1568000 | M26: =L26/E26 -> 789.12934 | N26: Safeway Rivermark ~2 mi | O26: Montague Elem 5/10 ~2.5 mi | P26: Kaiser Santa Clara ~5 mi | Q26: Same as NS-2. | R26: 12-15 min | S26: Townhouse (3-story) - not a detached house. | T26: 3 | U26: 3 | V26: 3 | W26: 4 | X26: =T26+U26+V26+2*W26 -> 17 | Y26: =RANK(X26,$X$2:$X$30) -> 16 | Z26: =IF(L26<='Read me'!$B$4,"Yes",IF(L26<='Read me'!$B$5,"Stretch","No")) -> Yes | AA26: Avoid
A27: NS-4 | B27: North San Jose | C27: 675 Epic Way Plan 5 (Pyrus Place), San Jose 95134 | D27: Open listing | E27: 2315 | F27: - | G27: 4/3.5 | H27: 2-car (est.) | I27: 2026 | J27: ~$375/mo | K27: Unverified (floor plan) | L27: 1798000 | M27: =L27/E27 -> 776.67387 | N27: Safeway Rivermark ~2 mi | O27: Montague Elem 5/10 ~2.5 mi | P27: Kaiser Santa Clara ~5 mi | Q27: Same as NS-2. | R27: 12-15 min | S27: Townhouse floor plan with no MLS record. | T27: 3 | U27: 3 | V27: 2 | W27: 1 | X27: =T27+U27+V27+2*W27 -> 10 | Y27: =RANK(X27,$X$2:$X$30) -> 29 | Z27: =IF(L27<='Read me'!$B$4,"Yes",IF(L27<='Read me'!$B$5,"Stretch","No")) -> Yes | AA27: Avoid
A28: SV-5 | B28: Sunnyvale | C28: 586 Borregas Ave, Sunnyvale 94085 | D28: Open listing | E28: 1516 | F28: 5,725 | G28: 3/2 | H28: NONE (driveway) | I28: 1949 | J28: None | K28: Active; price raised after offer deadline | L28: 1890000 | M28: =L28/E28 -> 1246.7018 | N28: Downtown Sunnyvale ~1 mi | O28: Bishop Elem 7/10, 0.3 mi | P28: El Camino MV / Kaiser SC ~4 mi | Q28: Flood risk 4/10; Hwy 101 ~0.4 mi. | R28: 12-18 min | S28: No garage (fails requirement). | T28: 3 | U28: 3 | V28: 2 | W28: 4 | X28: =T28+U28+V28+2*W28 -> 16 | Y28: =RANK(X28,$X$2:$X$30) -> 21 | Z28: =IF(L28<='Read me'!$B$4,"Yes",IF(L28<='Read me'!$B$5,"Stretch","No")) -> Yes | AA28: Avoid
A29: SV-6 | B29: Sunnyvale | C29: 225 S Mathilda Ave, Sunnyvale 94086 | D29: Open listing | E29: 1538 | F29: 5,000 | G29: 5/3 (incl. ADU) | H29: NONE (converted to ADU) | I29: 1920 | J29: None | K29: Active, relisted | L29: 1888000 | M29: =L29/E29 -> 1227.5683 | N29: Trader Joe's / downtown ~0.8 mi | O29: Cumberland Elem 10/10, 0.8 mi | P29: El Camino MV / Kaiser SC ~3.5 mi | Q29: Busy Mathilda frontage; Caltrain horns. | R29: 10-13 min | S29: No garage and main house only ~960 sq ft (fails requirements). | T29: 3 | U29: 2 | V29: 2 | W29: 4 | X29: =T29+U29+V29+2*W29 -> 15 | Y29: =RANK(X29,$X$2:$X$30) -> 26 | Z29: =IF(L29<='Read me'!$B$4,"Yes",IF(L29<='Read me'!$B$5,"Stretch","No")) -> Yes | AA29: Avoid
A30: NS-12 | B30: North San Jose | C30: 1280 Turrett Dr, San Jose 95131 | D30: Open listing | E30: 2032 | F30: 5,998 | G30: 5/3 (incl. JADU) | H30: NONE (converted to JADU) | I30: 1970 | J30: None | K30: Active; cut $475K | L30: 1275000 | M30: =L30/E30 -> 627.46063 | N30: Lundy Ave stores ~1 mi (est.) | O30: Vinci Park Elem 8/10, 0.4 mi | P30: Regional Medical Center SJ ~4 mi | Q30: Crime ~SJ average. | R30: 18-22 min | S30: No garage (fails requirement); priced to start bidding. | T30: 3 | U30: 3 | V30: 4 | W30: 4 | X30: =T30+U30+V30+2*W30 -> 18 | Y30: =RANK(X30,$X$2:$X$30) -> 11 | Z30: =IF(L30<='Read me'!$B$4,"Yes",IF(L30<='Read me'!$B$5,"Stretch","No")) -> Yes | AA30: Avoid
A32: Green = main pick; orange = avoid (townhouse or no garage). Distances and commute times are estimates. Blue cells are inputs.
